pyheroapi/__init__.py
pyheroapi/client.py
pyheroapi/easy_api.py
pyheroapi/exceptions.py
pyheroapi/models.py
pyheroapi/realtime.py
pyheroapi-0.4.3.dist-info/METADATA
pyheroapi-0.4.3.dist-info/WHEEL
pyheroapi-0.4.3.dist-info/licenses/LICENSE
pyheroapi-0.4.3.dist-info/RECORD
