Metadata-Version: 2.4
Name: pyheroapi
Version: 0.4.3
Summary: Easy-to-use Python client for Kiwoom Securities REST API with intuitive interface
Project-URL: Homepage, https://github.com/gejyn14/pyheroapi
Project-URL: Documentation, https://github.com/gejyn14/pyheroapi#readme
Project-URL: Repository, https://github.com/gejyn14/pyheroapi.git
Project-URL: Issues, https://github.com/gejyn14/pyheroapi/issues
Author-email: Kiwoom API Client <contact@example.com>
License-Expression: MIT
License-File: LICENSE
Keywords: api,kiwoom,korea,securities,stock,trading
Classifier: Development Status :: 4 - Beta
Classifier: Intended Audience :: Developers
Classifier: Intended Audience :: Financial and Insurance Industry
Classifier: License :: OSI Approved :: MIT License
Classifier: Operating System :: OS Independent
Classifier: Programming Language :: Python :: 3
Classifier: Programming Language :: Python :: 3.8
Classifier: Programming Language :: Python :: 3.9
Classifier: Programming Language :: Python :: 3.10
Classifier: Programming Language :: Python :: 3.11
Classifier: Programming Language :: Python :: 3.12
Classifier: Topic :: Office/Business :: Financial :: Investment
Classifier: Topic :: Software Development :: Libraries :: Python Modules
Requires-Python: >=3.8
Requires-Dist: pydantic>=2.0.0
Requires-Dist: requests>=2.25.0
Requires-Dist: typing-extensions>=4.0.0
Provides-Extra: all
Requires-Dist: websockets>=11.0.0; extra == 'all'
Provides-Extra: dev
Requires-Dist: bandit>=1.7.5; extra == 'dev'
Requires-Dist: black>=22.0.0; extra == 'dev'
Requires-Dist: doc8>=1.1.0; extra == 'dev'
Requires-Dist: flake8>=5.0.0; extra == 'dev'
Requires-Dist: httpx>=0.24.0; extra == 'dev'
Requires-Dist: isort>=5.0.0; extra == 'dev'
Requires-Dist: jupyter>=1.0.0; extra == 'dev'
Requires-Dist: memory-profiler>=0.60.0; extra == 'dev'
Requires-Dist: mypy>=1.0.0; extra == 'dev'
Requires-Dist: notebook>=6.5.0; extra == 'dev'
Requires-Dist: psutil>=5.9.0; extra == 'dev'
Requires-Dist: pydocstyle>=6.3.0; extra == 'dev'
Requires-Dist: pytest-asyncio>=0.21.0; extra == 'dev'
Requires-Dist: pytest-cov>=4.0.0; extra == 'dev'
Requires-Dist: pytest-json-report>=1.5.0; extra == 'dev'
Requires-Dist: pytest-mock>=3.10.0; extra == 'dev'
Requires-Dist: pytest-xdist>=3.0.0; extra == 'dev'
Requires-Dist: pytest>=7.0.0; extra == 'dev'
Requires-Dist: responses>=0.23.0; extra == 'dev'
Requires-Dist: safety>=2.3.0; extra == 'dev'
Requires-Dist: websockets>=11.0.0; extra == 'dev'
Provides-Extra: realtime
Requires-Dist: websockets>=11.0.0; extra == 'realtime'
